setup.cfg
setup.py
shellpy
shellpy.egg-info/PKG-INFO
shellpy.egg-info/SOURCES.txt
shellpy.egg-info/dependency_links.txt
shellpy.egg-info/entry_points.txt
shellpy.egg-info/requires.txt
shellpy.egg-info/top_level.txt
shellpython/__init__.py
shellpython/config.py
shellpython/constants.py
shellpython/core.py
shellpython/header.tpl
shellpython/header_root.tpl
shellpython/helpers.py
shellpython/importer.py
shellpython/locator.py
shellpython/preprocessor.py
shellpython/shellpy.py