Metadata-Version: 1.1
Name: shellpy
Version: 0.5.1
Summary: A convenient tool for shell scripting in python
Home-page: https://github.com/lamerman/shellpy/
Author: Alexander Ponomarev
Author-email: alexander996@yandex.ru
License: UNKNOWN
Download-URL: https://github.com/lamerman/shellpy/tarball/0.5.1
Keywords: shell,bash,sh
Platform: UNKNOWN
